flask_simplepay/__init__.py
flask_simplepay/core.py
flask_simplepay/model.py
Flask_SimplePay-1.1.dist-info/LICENSE
Flask_SimplePay-1.1.dist-info/METADATA
Flask_SimplePay-1.1.dist-info/WHEEL
Flask_SimplePay-1.1.dist-info/top_level.txt
Flask_SimplePay-1.1.dist-info/RECORD
