Metadata-Version: 2.1
Name: Flask-SimplePay
Version: 1.1
Summary: OTP SimplePay payment extension for Flask
Home-page: https://github.com/gerelorant/Flask-SimplePay
Author: Gere Lóránt
Author-email: Gere Lóránt <gerelorant@gmail.com>
License: MIT
Project-URL: Homepage, https://github.com/gerelorant/Flask-SimplePay
Classifier: Programming Language :: Python :: 3
Classifier: License :: OSI Approved :: MIT License
Classifier: Operating System :: OS Independent
Requires-Python: >=3.7
License-File: LICENSE
